arize/otel/__init__.py
arize/otel/otel.py
arize/otel/settings.py
arize/otel/version.py
arize_otel-0.10.0.dist-info/METADATA
arize_otel-0.10.0.dist-info/WHEEL
arize_otel-0.10.0.dist-info/licenses/LICENSE
arize_otel-0.10.0.dist-info/RECORD
