Metadata-Version: 2.4
Name: arize-otel
Version: 0.10.0
Summary: Helper package for OTEL setup to send traces to Arize & Phoenix
Project-URL: Documentation, https://docs.arize.com/arize/large-language-models/tracing
Project-URL: Issues, https://github.com/Arize-ai/arize-otel-python/issues
Project-URL: Source, https://github.com/Arize-ai/arize-otel-python
Project-URL: Changelog, https://github.com/Arize-ai/arize-otel-python/blob/main/CHANGELOG.md
Author-email: Arize AI <support@arize.com>
Maintainer-email: Arize AI <support@arize.com>
License: BSD
License-File: LICENSE
Keywords: Explainability,Monitoring,Observability,Tracing
Classifier: Development Status :: 5 - Production/Stable
Classifier: Intended Audience :: Developers
Classifier: Programming Language :: Python
Classifier: Programming Language :: Python :: 3.8
Classifier: Programming Language :: Python :: 3.9
Classifier: Programming Language :: Python :: 3.10
Classifier: Programming Language :: Python :: 3.11
Classifier: Programming Language :: Python :: 3.12
Classifier: Programming Language :: Python :: 3.13
Classifier: Topic :: Scientific/Engineering :: Artificial Intelligence
Classifier: Topic :: Software Development :: Libraries :: Python Modules
Classifier: Topic :: System :: Logging
Classifier: Topic :: System :: Monitoring
Requires-Python: <3.14,>=3.8
Requires-Dist: openinference-instrumentation>=0.1.22
Requires-Dist: openinference-semantic-conventions>=0.1.5
Requires-Dist: opentelemetry-exporter-otlp>=1.22
Requires-Dist: opentelemetry-proto>=1.12.0
Requires-Dist: opentelemetry-sdk>=1.22
